tomosegmemtv/__init__.py
tomosegmemtv/bibtex.py
tomosegmemtv/constants.py
tomosegmemtv/icon.png
tomosegmemtv/protocols.conf
tomosegmemtv/protocols/__init__.py
tomosegmemtv/protocols/protocol_annotate_membranes.py
tomosegmemtv/protocols/protocol_base.py
tomosegmemtv/protocols/protocol_resize_tomomask.py
tomosegmemtv/protocols/protocol_tomosegmentv.py
tomosegmemtv/tests/__init__.py
tomosegmemtv/tests/test_resize_tomomask.py
tomosegmemtv/tests/test_tomosegmemtv.py
tomosegmemtv/viewers/__init__.py
tomosegmemtv/viewers/annotation_results_viewer.py
tomosegmemtv/viewers/memb_annotator_results_tree.py
tomosegmemtv/viewers/viewers_data.py
tomosegmemtv/viewers_interactive/__init__.py
tomosegmemtv/viewers_interactive/memb_annotator_tomo_viewer.py
tomosegmemtv/viewers_interactive/memb_annotator_tree.py
scipion_em_tomosegmemtv-3.2.1.dist-info/LICENSE
scipion_em_tomosegmemtv-3.2.1.dist-info/METADATA
scipion_em_tomosegmemtv-3.2.1.dist-info/WHEEL
scipion_em_tomosegmemtv-3.2.1.dist-info/entry_points.txt
scipion_em_tomosegmemtv-3.2.1.dist-info/top_level.txt
scipion_em_tomosegmemtv-3.2.1.dist-info/RECORD
