Metadata-Version: 2.1
Name: scipion-em-tomosegmemtv
Version: 3.2.1
Summary: Scipion plugin for softare packages tomosegmemTV and membraneAnnotator.
Home-page: https://github.com/scipion-em/scipion-em-tomosegmemtv
Author: I2PC
Author-email: scipion@cnb.cis.es
License: UNKNOWN
Keywords: scipion cryoem cryoet imageprocessing scipion-3.0
Platform: UNKNOWN
Classifier: Development Status :: 5 - Production/Stable
Classifier: License :: OSI Approved :: GNU General Public License v3 (GPLv3)
Classifier: Programming Language :: Python :: 3
Requires-Dist: scipion-em-tomo>=3.9.1
Requires-Dist: mrcfile
Requires-Dist: scipy
